{"XML": {"comment": 28, "nFiles": 2, "code": 41, "blank": 7}, "C/C++ Header": {"comment": 3224, "nFiles": 97, "code": 4516, "blank": 1647}, "Markdown": {"comment": 0, "nFiles": 12, "code": 401, "blank": 116}, "Java": {"comment": 45, "nFiles": 3, "code": 88, "blank": 20}, "YAML": {"comment": 59, "nFiles": 2, "code": 127, "blank": 9}, "Python": {"comment": 560, "nFiles": 18, "code": 1352, "blank": 346}, "make": {"comment": 41, "nFiles": 4, "code": 56, "blank": 22}, "JavaScript": {"comment": 37, "nFiles": 2, "code": 152, "blank": 24}, "C++": {"comment": 4081, "nFiles": 128, "code": 22937, "blank": 3821}, "Windows Resource File": {"comment": 0, "nFiles": 1, "code": 44, "blank": 5}, "header": {"cloc_url": "github.com/AlDanial/cloc", "n_files": 534, "cloc_version": "1.76", "n_lines": 49734, "files_per_second": 316.267139009887, "lines_per_second": 29455.4866882354, "elapsed_seconds": 1.68844604492188}, "HTML": {"comment": 34, "nFiles": 2, "code": 341, "blank": 48}, "right": "2018-03-12", "Protocol Buffers": {"comment": 1450, "nFiles": 258, "code": 3112, "blank": 686}, "SUM": {"comment": 9628, "nFiles": 534, "code": 33316, "blank": 6790}, "Bourne Again Shell": {"comment": 43, "nFiles": 3, "code": 91, "blank": 25}, "Bourne Shell": {"comment": 26, "nFiles": 2, "code": 58, "blank": 14}, "left": "2018-03-11"}