{"XML": {"comment": 15, "nFiles": 1, "code": 12, "blank": 3}, "C/C++ Header": {"comment": 2361, "nFiles": 73, "code": 3136, "blank": 1179}, "Markdown": {"comment": 0, "nFiles": 6, "code": 184, "blank": 57}, "Java": {"comment": 15, "nFiles": 1, "code": 11, "blank": 5}, "YAML": {"comment": 36, "nFiles": 2, "code": 147, "blank": 9}, "Python": {"comment": 503, "nFiles": 17, "code": 1197, "blank": 327}, "make": {"comment": 72, "nFiles": 5, "code": 83, "blank": 42}, "JavaScript": {"comment": 17, "nFiles": 1, "code": 120, "blank": 15}, "C++": {"comment": 2464, "nFiles": 91, "code": 11028, "blank": 2196}, "header": {"cloc_url": "github.com/AlDanial/cloc", "n_files": 226, "cloc_version": "1.76", "n_lines": 26732, "files_per_second": 129.013843861451, "lines_per_second": 15260.1684694881, "elapsed_seconds": 1.75174999237061}, "HTML": {"comment": 34, "nFiles": 2, "code": 315, "blank": 45}, "right": "2018-01-06", "Protocol Buffers": {"comment": 441, "nFiles": 21, "code": 350, "blank": 139}, "left": "2018-01-05", "SUM": {"comment": 6010, "nFiles": 226, "code": 16689, "blank": 4033}, "Bourne Again Shell": {"comment": 26, "nFiles": 2, "code": 6, "blank": 2}, "Bourne Shell": {"comment": 26, "nFiles": 2, "code": 58, "blank": 14}, "INI": {"comment": 0, "nFiles": 2, "code": 42, "blank": 0}}